{
  "$schema": "http://schema.management.azure.com/schemas/2015-01-01/deploymentParameters.json#",
  "contentVersion": "1.0.0.0",
  "parameters": {
    "adminPassword": {
      "value": "hjkl6789HJKL"
    },
    "prefix": {
      "value": "MCLAB"
    },
    "vNetAddressSpace": {
      "value": "10.1.0.0/16"
    },
    "subnetCGF": {
      "value": "10.1.0.0/24"
    },
    "subnetWeb": {
      "value": "10.1.1.0/24"
    },
    "subnetGreen": {
      "value": "10.1.2.0/24"
    },
    "subnetBlue": {
      "value": "10.1.3.0/24"
    },
    "subnetRed": {
      "value": "10.1.99.0/24"
    },
    "imageSKU": {
      "value": "byol"
    },
    "vmSizeCGF": {
      "value": "Standard_DS1_v2"
    },
    "vmSizeWAF": {
      "value": "Standard_DS1_v2"
    },
    "": {
      "value": ""
    }
  }
}
